fairchem/data/omol/LICENSE.md
fairchem/data/omol/README.md
fairchem/data/omol/__init__.py
fairchem/data/omol/modules/evaluator.py
fairchem/data/omol/orca/__init__.py
fairchem/data/omol/orca/calc.py
fairchem/data/omol/orca/recipes.py
fairchem/data/omol/orca/basis/def2-tzvpd.bas
fairchem_data_omol-0.1.1.dist-info/METADATA
fairchem_data_omol-0.1.1.dist-info/WHEEL
fairchem_data_omol-0.1.1.dist-info/RECORD
