Metadata-Version: 2.4
Name: fairchem-data-omol
Version: 0.1.1
Summary: Code for generating OMOL input configurations
Project-URL: repository, https://github.com/facebookresearch/fairchem/tree/main/src/fairchem/data/omol
Project-URL: documentation, https://fair-chem.github.io/
License: MIT License
Requires-Dist: ase
Requires-Dist: sella
